ho/__init__.py
ho/hello.py
ho_hello-0.0.1.dist-info/LICENSE
ho_hello-0.0.1.dist-info/METADATA
ho_hello-0.0.1.dist-info/WHEEL
ho_hello-0.0.1.dist-info/top_level.txt
ho_hello-0.0.1.dist-info/RECORD
