Metadata-Version: 2.1
Name: ho-hello
Version: 0.0.1
Summary: Hello package for Ho
Home-page: https://github.com/pypa/sampleproject
Author: amansman77
Author-email: amansman77@gmail.com
License: UNKNOWN
Platform: UNKNOWN
Classifier: Programming Language :: Python :: 3
Classifier: License :: OSI Approved :: MIT License
Classifier: Operating System :: OS Independent
Requires-Python: >=3.6
